{"@id":1,"@type":"Modelo.Restaurante","usuarios":[{"@id":2,"@type":"Modelo.Usuarios.Cajero","restaurante":{"@ref":1},"nombre":null,"cedula":null,"telefono":null,"sexo":"\u0000","fechaNacimiento":null,"nombreUsuario":null,"password":null}],"productos":[],"combos":[],"facturas":[{"@type":"Modelo.Facturacion.Factura","numFactura":2,"fecha":{"date":{"year":2015,"month":5,"day":27},"time":{"hour":22,"minute":10,"second":23,"nano":824000000}},"items":[],"cajero":{"@ref":2},"estado":{"name":"CREADA","ordinal":0}}]}